<?xml version="1.1" encoding="UTF-8"?>
	<specification xmlns:xsi="http://www.w3.org/2001/XMLSchema-instance"
		xsi:noNamespaceSchemaLocation="schemas/specification.xsd" defaultVersion="1.2.1"
		defaultWorkgroup="sd" url="http://www.hl7.org/implement/standards/product_brief.cfm?product_id=386">
		<!--<specification xmlns:xsi="http://www.w3.org/2001/XMLSchema-instance"
 xsi:noNamespaceSchemaLocation="schemas/specification.xsd" defaultVersion="STU2"
 defaultWorkgroup="sd">-->
		<version code="1.2.1" url="https://www.hl7.org/dstucomments/showdetail.cfm?dstuid=250" deprecated="false"/>
		<version code="1.2.0" url="https://www.hl7.org/dstucomments/showdetail.cfm?dstuid=292" deprecated="true"/>
		<version code="1.1.0" url="https://www.hl7.org/dstucomments/showdetail.cfm?dstuid=145" deprecated="true"/>
		<page key="NA" name="(NA)"/>
		<page key="many" name="(many)"/>
		<page key="usecases" name="Use Cases"/>
		<page key="narratives" name="Narrative Guidance"/>
		<page key="templates" name="Templates"/>
		<page key="figures-examples" name="Figures and Examples"/>
		<page key="valuesets" name="Value sets"/>
		<page key="samplefiles" name="Sample Files"/>
		<page key="schematron" name="Schematron Validation Files"/>
	</specification>
