<?xml version="1.0" encoding="UTF-8"?>
<!-- edited with XMLSpy v2019 rel. 3 sp1 (x64) (http://www.altova.com) by  (Cerner Corporation) -->
<specification url="http://www.hl7.org/implement/standards/product_brief.cfm?product_id=486" defaultWorkgroup="sd" defaultVersion="1.0" xmlns:xsi="http://www.w3.org/2001/XMLSchema-instance" xsi:noNamespaceSchemaLocation="../schemas/specification.xsd">
	<version code="1.0"/>
	<page key="udi" deprecated="false" workgroup="sd" url="http:www.hl7.orgimplementstandardsproduct_brief.cfmproduct_id486" name="HL7 CDA® R2 Implementation Guide: C-CDA Supplemental Templates for Unique Device Identifier (UDI) for Implantable Medical Devices, Release 1 - US Realm"/>
		<page key="NA" name="(NA)"/>
	<page key="many" name="(many)"/>
	<page key="profiles" name="(profiles)"/>
	<page key="overview" name="Overview"/>
	<page key="usecases" name="Use Cases"/>
	<page key="documentation" name="Documentation" deprecated="true"/>
	<page key="index" name="Index" deprecated="true"/>
	<page key="narratives" name="Narrative Guidance"/>
	<page key="templates" name="Templates"/>
	<page key="figures" name="Figures and Examples"/>
	<page key="valuesets" name="Value sets"/>
	<page key="samplefiles" name="Sample Files"/>
	<page key="validationfiles" name="Validation Files"/>
	<page key="schematron" name="Schematron"/>
</specification>
