<?xml version="1.0" encoding="UTF-8"?>
<specification
  url="http://hl7.org/fhir/us/davinci-alerts"
  ciUrl="http://build.fhir.org/ig/HL7/davinci-alerts"
  defaultWorkgroup="HL7 International - Infrastructure and Messaging Work Group"
  xmlns:xsi="http://www.w3.org/2001/XMLSchema-instance"
  defaultVersion="0.2.0"
  xsi:noNamespaceSchemaLocation="../schemas/specification.xsd">
  <version code="0.2.1"/>
  <version code="0.2.0"/>
  <artifactPageExtension value="-definitions"/>
  <artifactPageExtension value="-examples"/>
  <artifactPageExtension value="-mappings"/>
  <artifact name="Bundle" key="Bundle" deprecated="true"/>
  <artifact name="Coverage" key="Coverage" deprecated="true"/>
  <artifact name="Condition" key="Condition" deprecated="true"/>
  <artifact name="MessageDefinition" key="MessageDefinition" deprecated="true"/>
  <artifact name="ValueSet" key="ValueSet" deprecated="true"/>
  <artifact name="GraphDefinition" key="GraphDefinition" deprecated="true"/>
  <artifact name="CodeSystem" key="CodeSystem" deprecated="true"/>
  <artifact name="CapabilityStatement" key="CapabilityStatement" deprecated="true"/>
  <artifact name="Encounter" key="Encounter" deprecated="true"/>
  <artifact name="StructureDefinition" key="StructureDefinition" deprecated="true"/>
  <artifact name="MessageHeader" key="MessageHeader" deprecated="true"/>  <page name="(NA)" key="NA"/>
  <page name="(many)" key="many"/>
  <page name="(methodology)" key="methodology"/>
  <page name="(profiles)" key="profiles"/>
  <page name="Schemas &amp; Schematrons" key="schemas-schematrons" deprecated="true"/>
  <page name="Home (index)" key="index" url="index" deprecated="true"/>
  <page name="Framework" key="guidance" url="guidance" deprecated="true"/>
  <page name="Admit/Discharge Use Case" key="profiles" url="profiles" deprecated="true"/>
  <page name="StructureDefinition Admit Discharge Notification Condition" key="StructureDefinition-admit-discharge-notification-condition" url="StructureDefinition-admit-discharge-notification-condition" deprecated="true"/>
  <page name="StructureDefinition Notifications GraphDefinition" key="StructureDefinition-notifications-graphdefinition" url="StructureDefinition-notifications-graphdefinition" deprecated="true"/>
  <page name="StructureDefinition Admit Discharge Notification Encounter" key="StructureDefinition-admit-discharge-notification-encounter" url="StructureDefinition-admit-discharge-notification-encounter" deprecated="true"/>
  <page name="StructureDefinition Discharge Notification MessageHeader" key="StructureDefinition-discharge-notification-messageheader" url="StructureDefinition-discharge-notification-messageheader" deprecated="true"/>
  <page name="StructureDefinition Admit Discharge Notification Coverage" key="StructureDefinition-admit-discharge-notification-coverage" url="StructureDefinition-admit-discharge-notification-coverage" deprecated="true"/>
  <page name="StructureDefinition Admit Notification MessageHeader" key="StructureDefinition-admit-notification-messageheader" url="StructureDefinition-admit-notification-messageheader" deprecated="true"/>
  <page name="StructureDefinition Notifications Bundle" key="StructureDefinition-notifications-bundle" url="StructureDefinition-notifications-bundle" deprecated="true"/>
  <page name="StructureDefinition Notifications MessageDefinition" key="StructureDefinition-notifications-messagedefinition" url="StructureDefinition-notifications-messagedefinition" deprecated="true"/>
  <page name="StructureDefinition Notifications MessageHeader" key="StructureDefinition-notifications-messageheader" url="StructureDefinition-notifications-messageheader" deprecated="true"/>
  <page name="Bundle Definitions" key="bundles" url="bundles" deprecated="true"/>
  <page name="MessageDefinition Notification Admit" key="MessageDefinition-notification-admit" url="MessageDefinition-notification-admit" deprecated="true"/>
  <page name="MessageDefinition Notification Discharge" key="MessageDefinition-notification-discharge" url="MessageDefinition-notification-discharge" deprecated="true"/>
  <page name="GraphDefinition Admit Discharge" key="GraphDefinition-admit-discharge" url="GraphDefinition-admit-discharge" deprecated="true"/>
  <page name="Terminology" key="terminology" url="terminology" deprecated="true"/>
  <page name="ValueSet Notification Event" key="ValueSet-notification-event" url="ValueSet-notification-event" deprecated="true"/>
  <page name="CodeSystem Notification Event" key="CodeSystem-notification-event" url="CodeSystem-notification-event" deprecated="true"/>
  <page name="Capability Statements" key="capstatements" url="capstatements" deprecated="true"/>
  <page name="CapabilityStatement Notification Initiator" key="CapabilityStatement-notification-sender" url="CapabilityStatement-notification-sender" deprecated="true"/>
  <page name="CapabilityStatement Query Requester" key="CapabilityStatement-query-requester" url="CapabilityStatement-query-requester" deprecated="true"/>
  <page name="CapabilityStatement Notification Receiver" key="CapabilityStatement-notification-receiver" url="CapabilityStatement-notification-receiver" deprecated="true"/>
  <page name="CapabilityStatement Query Responder" key="CapabilityStatement-query-responder" url="CapabilityStatement-query-responder" deprecated="true"/>
  <page name="Security" key="security" url="security" deprecated="true"/>
  <page name="All Examples" key="all-examples" url="all-examples" deprecated="true"/>
  <page name="Downloads" key="downloads" url="downloads" deprecated="true"/>
  <page name="Table of Contents" key="toc" url="toc" deprecated="true"/>
  <page name="Change Log" key="change-notes" url="change-notes" deprecated="true"/>  <page name="Implementation Registry (registry/iglist)" key="iglist" url="registry" deprecated="true"/>
  <page name="Terminologies - Systems" key="terminologies-systems" url="terminologies-systems" deprecated="true"/>
  <page name="implementation" key="implementation" url="implementation" deprecated="true"/>
  <page name="terminologies" key="terminologies" url="terminologies" deprecated="true"/>
</specification>
