<?xml version="1.0" encoding="UTF-8"?>
<specification xmlns:xsi="http://www.w3.org/2001/XMLSchema-instance" ballotUrl="http://hl7.org/fhir/us/medmorph-research-dex/2022Jan" ciUrl="http://build.fhir.org/ig/HL7/fhir-medmorph-research-dex" defaultVersion="0.1.0" defaultWorkgroup="pher" gitUrl="https://github.com/HL7/fhir-medmorph" url="http://hl7.org/fhir/us/medmorph-research-dex">
<version code="current" url="http://build.fhir.org/ig/HL7/fhir-medmorph-research-dex"/>
<version code="0.1.0" url="http://hl7.org/fhir/us/medmorph-research-dex/2022Jan"/>
<artifactPageExtension value="-definitions"/>
<artifactPageExtension value="-examples"/>
<artifactPageExtension value="-mappings"/>
<artifact id="Endpoint/example-healthcare-endpoint" key="Endpoint-example-healthcare-endpoint" name="Endpoint Example"/>
<artifact id="CapabilityStatement/medmorph-research-dex-ehr" key="CapabilityStatement-medmorph-research-dex-ehr" name="MedMorph Research Data Exchange EHR Capability Statement"/>
<artifact id="StructureDefinition/medmorph-research-dex-plandefinition" key="StructureDefinition-medmorph-research-dex-plandefinition" name="MedMorph Research Data Exchange PlanDefinition"/>
<artifact id="Organization/example-healthcare-org" key="Organization-example-healthcare-org" name="Organization Example"/>
<artifact id="Patient/1" key="Patient-1" name="Patient Example"/>
<artifact id="Practitioner/1" key="Practitioner-1" name="Practitioner Example"/>
<artifact id="PlanDefinition/plandefinition-example" key="PlanDefinition-plandefinition-example" name="Research Data Extraction Knowledge Artifact Example"/>
<artifact id="Group/group-example-research" key="Group-group-example-research" name="Research Participants Group Example"/>
<page key="NA" name="(NA)"/>
<page key="many" name="(many)"/>
<page key="artifacts" name="Artifacts Summary"/>
<page key="spec" name="Detailed Specification"/>
<page key="changes" name="IG Change History"/>
<page key="index" name="MedMorph Research Content IG Home"/>
<page key="toc" name="Table of Contents"/>
<page key="usecases" name="Use Cases"/>
<page key="downloads" name="Useful Downloads"/>
</specification>
